LICENSE
README.md
setup.cfg
setup.py
torchreid/__init__.py
torchreid/setup.py
torchreid.egg-info/PKG-INFO
torchreid.egg-info/SOURCES.txt
torchreid.egg-info/dependency_links.txt
torchreid.egg-info/requires.txt
torchreid.egg-info/top_level.txt
torchreid/reid/__init__.py
torchreid/reid/data/__init__.py
torchreid/reid/data/datamanager.py
torchreid/reid/data/sampler.py
torchreid/reid/data/transforms.py
torchreid/reid/data/datasets/__init__.py
torchreid/reid/data/datasets/dataset.py
torchreid/reid/data/datasets/image/__init__.py
torchreid/reid/data/datasets/image/cuhk01.py
torchreid/reid/data/datasets/image/cuhk02.py
torchreid/reid/data/datasets/image/cuhk03.py
torchreid/reid/data/datasets/image/cuhksysu.py
torchreid/reid/data/datasets/image/dukemtmcreid.py
torchreid/reid/data/datasets/image/grid.py
torchreid/reid/data/datasets/image/ilids.py
torchreid/reid/data/datasets/image/market1501.py
torchreid/reid/data/datasets/image/msmt17.py
torchreid/reid/data/datasets/image/prid.py
torchreid/reid/data/datasets/image/sensereid.py
torchreid/reid/data/datasets/image/university1652.py
torchreid/reid/data/datasets/image/viper.py
torchreid/reid/data/datasets/video/__init__.py
torchreid/reid/data/datasets/video/dukemtmcvidreid.py
torchreid/reid/data/datasets/video/ilidsvid.py
torchreid/reid/data/datasets/video/mars.py
torchreid/reid/data/datasets/video/prid2011.py
torchreid/reid/engine/__init__.py
torchreid/reid/engine/engine.py
torchreid/reid/engine/image/__init__.py
torchreid/reid/engine/image/softmax.py
torchreid/reid/engine/image/triplet.py
torchreid/reid/engine/video/__init__.py
torchreid/reid/engine/video/softmax.py
torchreid/reid/engine/video/triplet.py
torchreid/reid/losses/__init__.py
torchreid/reid/losses/cross_entropy_loss.py
torchreid/reid/losses/hard_mine_triplet_loss.py
torchreid/reid/metrics/__init__.py
torchreid/reid/metrics/accuracy.py
torchreid/reid/metrics/distance.py
torchreid/reid/metrics/rank.py
torchreid/reid/metrics/rank_cylib/__init__.py
torchreid/reid/metrics/rank_cylib/setup.py
torchreid/reid/metrics/rank_cylib/test_cython.py
torchreid/reid/models/__init__.py
torchreid/reid/models/densenet.py
