Metadata-Version: 2.1
Name: torchreid
Version: 0.2.0
Summary: Torchreid-Pip: Deep learning person re-identification in PyTorch.
Home-page: https://github.com/goksenin-uav/torchreid-pip
Author: kadirnar
License: MIT
Keywords: machine-learning,deep-learning,ml,pytorch,vision,loss,image-classification,video-classification
Platform: UNKNOWN
Classifier: Development Status :: 5 - Production/Stable
Classifier: Operating System :: OS Independent
Classifier: Intended Audience :: Developers
Classifier: Intended Audience :: Science/Research
Classifier: Programming Language :: Python :: 3
Classifier: Programming Language :: Python :: 3.7
Classifier: Programming Language :: Python :: 3.8
Classifier: Programming Language :: Python :: 3.9
Classifier: Topic :: Software Development :: Libraries
Classifier: Topic :: Software Development :: Libraries :: Python Modules
Classifier: Topic :: Education
Classifier: Topic :: Scientific/Engineering
Classifier: Topic :: Scientific/Engineering :: Artificial Intelligence
Requires-Python: >=3.7
Provides-Extra: tests
Provides-Extra: dev
License-File: LICENSE
